repeater/__init__.py
repeater/program.py
textrepeater_tocg-0.0.9.dist-info/METADATA
textrepeater_tocg-0.0.9.dist-info/WHEEL
textrepeater_tocg-0.0.9.dist-info/top_level.txt
textrepeater_tocg-0.0.9.dist-info/RECORD
